asynciotimemachine.py
asynciotimemachine-0.3.0.dist-info/AUTHORS.rst
asynciotimemachine-0.3.0.dist-info/LICENSE
asynciotimemachine-0.3.0.dist-info/METADATA
asynciotimemachine-0.3.0.dist-info/WHEEL
asynciotimemachine-0.3.0.dist-info/top_level.txt
asynciotimemachine-0.3.0.dist-info/RECORD
