Metadata-Version: 2.1
Name: asynciotimemachine
Version: 0.3.0
Summary: Monkey-patches asyncio.AbstractEventLoop so as to make it think it lives in the future.
Home-page: https://github.com/astralblue/asynciotimemachine
Author: Eugene M. Kim
Author-email: astralblue@gmail.com
License: MIT license
Keywords: asynciotimemachine
Platform: UNKNOWN
Classifier: Development Status :: 2 - Pre-Alpha
Classifier: Intended Audience :: Developers
Classifier: License :: OSI Approved :: MIT License
Classifier: Natural Language :: English
Classifier: Programming Language :: Python :: 3
Classifier: Programming Language :: Python :: 3.6
Classifier: Programming Language :: Python :: 3.7
Classifier: Programming Language :: Python :: 3.8
Classifier: Programming Language :: Python :: 3.9
License-File: LICENSE
License-File: AUTHORS.rst
